{
	"configurations" : 
	[
		{
			"directories" : 
			[
				{
					"build" : ".",
					"hasInstallRule" : true,
					"jsonFile" : "directory-.-Debug-0e270076524fc1d22384.json",
					"minimumCMakeVersion" : 
					{
						"string" : "3.1.0"
					},
					"projectIndex" : 0,
					"source" : ".",
					"targetIndexes" : 
					[
						0
					]
				}
			],
			"name" : "Debug",
			"projects" : 
			[
				{
					"directoryIndexes" : 
					[
						0
					],
					"name" : "CME",
					"targetIndexes" : 
					[
						0
					]
				}
			],
			"targets" : 
			[
				{
					"directoryIndex" : 0,
					"id" : "cme::@6890427a1f51a3e7e1df",
					"jsonFile" : "target-cme-Debug-4f2dc3127b9e2ee6634a.json",
					"name" : "cme",
					"projectIndex" : 0
				}
			]
		}
	],
	"kind" : "codemodel",
	"paths" : 
	{
		"build" : "/home/wilfc/github/coastalme_TESTING/src/cmake-build-debug",
		"source" : "/home/wilfc/github/coastalme_TESTING/src"
	},
	"version" : 
	{
		"major" : 2,
		"minor" : 3
	}
}
